pymp_proctor/__init__.py
pymp_proctor/applications.py
pymp_proctor/proctor.py
pymp_proctor-0.1.5.dist-info/LICENSE
pymp_proctor-0.1.5.dist-info/WHEEL
pymp_proctor-0.1.5.dist-info/METADATA
pymp_proctor-0.1.5.dist-info/RECORD
