Metadata-Version: 2.1
Name: pymp-proctor
Version: 0.1.5
Summary: MediaPipe Proctoring Toolkit Python Implementation
Home-page: https://github.com/sawthiha/pymp_proctor
License: Apache Software License 2.0
Author: sawthiha
Author-email: saw1996.dev@gmail.com
Requires-Python: >=3.7,<4.0
Classifier: Development Status :: 3 - Alpha
Classifier: Intended Audience :: Developers
Classifier: License :: OSI Approved :: Apache Software License
Classifier: License :: Other/Proprietary License
Classifier: Operating System :: OS Independent
Classifier: Programming Language :: Python :: 3
Classifier: Programming Language :: Python :: 3.7
Classifier: Programming Language :: Python :: 3.8
Classifier: Programming Language :: Python :: 3.9
Classifier: Programming Language :: Python :: 3.10
Classifier: Programming Language :: Python :: 3.11
Classifier: Programming Language :: Python :: 3
Classifier: Programming Language :: Python :: 3.7
Classifier: Programming Language :: Python :: 3.8
Classifier: Programming Language :: Python :: 3.9
Classifier: Topic :: Software Development :: Libraries :: Python Modules
Requires-Dist: importlib_metadata (>=4.5.0,<5.0.0) ; python_version < "3.8"
Requires-Dist: mediapipe (==0.8.9.1)
Requires-Dist: protobuf (>=3.20.0,<3.21.0)
Project-URL: Repository, https://github.com/sawthiha/pymp_proctor
